scalr/__init__.py
scalr/data_ingestion_pipeline.py
scalr/eval_and_analysis_pipeline.py
scalr/feature_extraction_pipeline.py
scalr/model_training_pipeline.py
scalr/analysis/__init__.py
scalr/analysis/_analyser.py
scalr/analysis/dge_lmem.py
scalr/analysis/dge_pseudobulk.py
scalr/analysis/evaluation.py
scalr/analysis/gene_recall_curve.py
scalr/analysis/heatmap.py
scalr/analysis/roc_auc.py
scalr/analysis/test_dge_lmem.py
scalr/analysis/test_dge_pseudobulk.py
scalr/data/__init__.py
scalr/data/preprocess/__init__.py
scalr/data/preprocess/_preprocess.py
scalr/data/preprocess/sample_norm.py
scalr/data/preprocess/standard_scale.py
scalr/data/preprocess/test_sample_norm.py
scalr/data/preprocess/test_standard_scale.py
scalr/data/split/__init__.py
scalr/data/split/_split.py
scalr/data/split/group_splitter.py
scalr/data/split/stratified_group_splitter.py
scalr/data/split/stratified_splitter.py
scalr/feature/__init__.py
scalr/feature/feature_subsetting.py
scalr/feature/scoring/__init__.py
scalr/feature/scoring/_scoring.py
scalr/feature/scoring/linear_scorer.py
scalr/feature/scoring/shap_scorer.py
scalr/feature/selector/__init__.py
scalr/feature/selector/_selector.py
scalr/feature/selector/abs_mean.py
scalr/feature/selector/classwise_abs.py
scalr/feature/selector/classwise_promoters.py
scalr/nn/__init__.py
scalr/nn/callbacks/__init__.py
scalr/nn/callbacks/_callbacks.py
scalr/nn/callbacks/early_stopping.py
scalr/nn/callbacks/model_checkpoint.py
scalr/nn/callbacks/tensorboard_logger.py
scalr/nn/callbacks/test_early_stopping.py
scalr/nn/dataloader/__init__.py
scalr/nn/dataloader/_dataloader.py
scalr/nn/dataloader/simple_dataloader.py
scalr/nn/dataloader/simple_metadataloader.py
scalr/nn/dataloader/test_simple_dataloader.py
scalr/nn/dataloader/test_simple_metadataloader.py
scalr/nn/loss/__init__.py
scalr/nn/loss/_loss.py
scalr/nn/model/__init__.py
scalr/nn/model/_model.py
scalr/nn/model/sequential_model.py
scalr/nn/model/shap_model.py
scalr/nn/trainer/__init__.py
pyscalr-1.1.0.dist-info/METADATA
pyscalr-1.1.0.dist-info/WHEEL
pyscalr-1.1.0.dist-info/licenses/LICENSE
pyscalr-1.1.0.dist-info/RECORD
