Metadata-Version: 2.4
Name: pyscaLR
Version: 1.1.0
Summary: scaLR: Single cell analysis using low resource.
Project-URL: Repository, https://github.com/infocusp/scaLR.git
Project-URL: Homepage, https://github.com/infocusp/scaLR
Project-URL: Issues, https://github.com/infocusp/scaLR/issues
Author-email: Infocusp <saurabh@infocusp.com>
License-File: LICENSE
Classifier: Intended Audience :: Science/Research
Classifier: Operating System :: OS Independent
Classifier: Programming Language :: Python :: 3.9
Requires-Python: >=3.10
Requires-Dist: anndata==0.10.9
Requires-Dist: isort==5.13.2
Requires-Dist: loky==3.4.1
Requires-Dist: memory-profiler==0.61.0
Requires-Dist: pillow==10.4.0
Requires-Dist: pre-commit==4.0.1
Requires-Dist: pydeseq2==0.4.11
Requires-Dist: pyparsing==3.2.0
Requires-Dist: pytest==8.3.3
Requires-Dist: pyyaml==6.0.2
Requires-Dist: scanpy==1.10.3
Requires-Dist: scikit-learn==1.5.2
Requires-Dist: shap==0.46.0
Requires-Dist: tensorboard==2.17.0
Requires-Dist: toml==0.10.2
Requires-Dist: torch==2.4.1
Requires-Dist: tqdm==4.66.5
Requires-Dist: yapf==0.40.2
